demux_Striping/probador.v
module probador (
    output reg clk_f,
    output reg clk_2f,
    output reg reset_L,
    output reg selector,
    output reg [31:0] data_in,
    output reg valid_in,
    input [31:0] data_out0,
    input [31:0] data_out1,
    input valid_out_0,
    input valid_out_1);

    initial begin
        $dumpfile("mux.vcd");	// Nombre de archivo del "dump"
		$dumpvars;			// Directiva para "dumpear" variables

        // valores iniciales
        reset_L <= 0;
        valid_in <= 0;

        @(posedge clk_2f);

        @(posedge clk_2f);

        @(posedge clk_2f);
        reset_L <= 1;

        @(posedge clk_2f);
        data_in <= 'hEEEEEEEE; // numero 0xEEEEEEEE
        valid_in <= 1;

        @(posedge clk_2f);
        data_in <= data_in + 1;
        valid_in <= 1;

        @(posedge clk_2f);
        data_in <= data_in + 1;
        valid_in <= 1;

        @(posedge clk_2f);
        data_in <= data_in + 1;
        valid_in <= 1;
        
        @(posedge clk_2f);
        valid_in <= 0;

        @(posedge clk_2f);

        @(posedge clk_2f);

        @(posedge clk_2f);

        @(posedge clk_2f);

        @(posedge clk_2f);


        $finish;
    end

    // clocks
    initial clk_f <= 0;
    initial clk_2f <= 1;

    always #20 clk_f <= ~clk_f; //hace toggle cada 20 nanosegundos
    always #10 clk_2f <= ~clk_2f; //hace toggle cada 10 nanosegundos

    // selector
    initial selector <= 0;

    // El selector se hace 0 cuando el valid se hace uno.
    always @ (valid_in) begin
        if(valid_in == 1) begin
            selector = 0;
        end
    end

    always #20 selector <= ~selector; // hace toggle a la misma frecuencia que clk_f

endmodule

demux_Striping/demux_striping.v
module demux_striping (
    input clk_f,
    input reset_L,
    input selector,
    input [31:0] data_in,
    input valid_in,
    output reg [31:0] data_out0,
    output reg [31:0] data_out1,
    output reg valid_out_0,
    output reg valid_out_1);

    reg [31:0] q1, q2; //aqui se almacena la salida del mux    
    reg valid1, valid2; //valor que se va a guardar para pasarlo al final

    always @ (*) begin
        
        if (selector == 0)begin
            q1 = data_in;
            valid1 = valid_in;
        end

        else begin
            q2 = data_in;
            valid2 = valid_in;
        end

    end

    always @ (posedge clk_f) begin

        if (reset_L == 0) begin // Ambas salidas serian puros ceros 
            data_out0 <= 32'b0;
            data_out1 <= 32'b0; 
            valid_out_0 <= 0;
            valid_out_1 <= 0;
        end

        if (reset_L == 1) begin
            data_out0 <= q1;
            valid_out_0 <= valid1;

            data_out1 <= q2;
            valid_out_1 <= valid2;
        end 

    end


endmodule

demux_Striping/bancoDePruebas.v
`timescale 	1ns				/ 100ps

`include "demux_striping.v"
`include "probador.v"

module BancoPruebas;

    wire clk_f, clk_2f, reset_L, selector, valid_in, valid_out_0, valid_out_1;
    wire [31:0] data_in, data_out0, data_out1;

    demux_striping cond ( /*AUTOINST*/
			 // Outputs
			 .data_out0		(data_out0[31:0]),
			 .data_out1		(data_out1[31:0]),
			 .valid_out_0		(valid_out_0),
			 .valid_out_1		(valid_out_1),
			 // Inputs
			 .clk_f			(clk_f),
			 .reset_L		(reset_L),
			 .selector		(selector),
			 .data_in		(data_in[31:0]),
			 .valid_in		(valid_in));

    probador probador_ (/*AUTOINST*/
			// Outputs
			.clk_f		(clk_f),
			.clk_2f		(clk_2f),
			.reset_L	(reset_L),
			.selector	(selector),
			.data_in	(data_in[31:0]),
			.valid_in	(valid_in),
			// Inputs
			.data_out0	(data_out0[31:0]),
			.data_out1	(data_out1[31:0]),
			.valid_out_0	(valid_out_0),
			.valid_out_1	(valid_out_1));

endmodule

demux_Striping/mux.vcd
$date
	Sun Sep 20 23:30:57 2020
$end
$version
	Icarus Verilog
$end
$timescale
	100ps
$end
$scope module BancoPruebas $end
$var wire 1 ! valid_out_1 $end
$var wire 1 " valid_out_0 $end
$var wire 1 # valid_in $end
$var wire 1 $ selector $end
$var wire 1 % reset_L $end
$var wire 32 & data_out1 [31:0] $end
$var wire 32 ' data_out0 [31:0] $end
$var wire 32 ( data_in [31:0] $end
$var wire 1 ) clk_f $end
$var wire 1 * clk_2f $end
$scope module cond $end
$var wire 1 # valid_in $end
$var wire 1 $ selector $end
$var wire 1 % reset_L $end
$var wire 32 + data_in [31:0] $end
$var wire 1 ) clk_f $end
$var reg 32 , data_out0 [31:0] $end
$var reg 32 - data_out1 [31:0] $end
$var reg 32 . q1 [31:0] $end
$var reg 32 / q2 [31:0] $end
$var reg 1 0 valid1 $end
$var reg 1 1 valid2 $end
$var reg 1 " valid_out_0 $end
$var reg 1 ! valid_out_1 $end
$upscope $end
$scope module probador_ $end
$var wire 32 2 data_out0 [31:0] $end
$var wire 32 3 data_out1 [31:0] $end
$var wire 1 " valid_out_0 $end
$var wire 1 ! valid_out_1 $end
$var reg 1 * clk_2f $end
$var reg 1 ) clk_f $end
$var reg 32 4 data_in [31:0] $end
$var reg 1 % reset_L $end
$var reg 1 $ selector $end
$var reg 1 # valid_in $end
$upscope $end
$upscope $end
$enddefinitions $end
#0
$dumpvars
bx 4
bx 3
bx 2
x1
00
bx /
bx .
bx -
bx ,
bx +
1*
0)
bx (
bx '
bx &
0%
0$
0#
x"
x!
$end
#100
0*
#200
0!
0"
b0 &
b0 -
b0 3
b0 '
b0 ,
b0 2
01
1*
1$
1)
#300
0*
#400
1%
1*
0$
0)
#500
0*
#600
10
b11101110111011101110111011101110 .
11
b11101110111011101110111011101110 /
1#
b11101110111011101110111011101110 (
b11101110111011101110111011101110 +
b11101110111011101110111011101110 4
bx &
bx -
bx 3
bx '
bx ,
bx 2
1*
0$
1)
#700
0*
#800
b11101110111011101110111011101111 /
b11101110111011101110111011101111 (
b11101110111011101110111011101111 +
b11101110111011101110111011101111 4
1*
1$
0)
#900
0*
#1000
b11101110111011101110111011110000 (
b11101110111011101110111011110000 +
b11101110111011101110111011110000 4
1!
b11101110111011101110111011101111 &
b11101110111011101110111011101111 -
b11101110111011101110111011101111 3
1"
b11101110111011101110111011101110 '
b11101110111011101110111011101110 ,
b11101110111011101110111011101110 2
b11101110111011101110111011110000 .
1*
0$
1)
#1100
0*
#1200
b11101110111011101110111011110001 (
b11101110111011101110111011110001 +
b11101110111011101110111011110001 4
b11101110111011101110111011110001 /
1*
1$
0)
#1300
0*
#1400
00
0#
b11101110111011101110111011110001 &
b11101110111011101110111011110001 -
b11101110111011101110111011110001 3
b11101110111011101110111011110000 '
b11101110111011101110111011110000 ,
b11101110111011101110111011110000 2
b11101110111011101110111011110001 .
1*
0$
1)
#1500
0*
#1600
01
1*
1$
0)
#1700
0*
#1800
0!
0"
b11101110111011101110111011110001 '
b11101110111011101110111011110001 ,
b11101110111011101110111011110001 2
1*
0$
1)
#1900
0*
#2000
1*
1$
0)
#2100
0*
#2200
1*
0$
1)
#2300
0*
#2400
1*
1$
0)
